<?xml version="1.0" encoding="UTF-8"?>
<!DOCTYPE mapper PUBLIC "-//mybatis.org//DTD Mapper 3.0//EN" "http://mybatis.org/dtd/mybatis-3-mapper.dtd" >
<mapper namespace="org.mu.opencomm.code.org.mu.cloudservice.repository.StatRepository" >
	
	<select id="getValues" resultType="long">
		SELECT sum FROM stat_download WHERE id = #{id} AND <![CDATA[ `date` >= #{from} AND `date` <= #{to} ]]>
	</select>
	
	<select id="exist" resultType="boolean">
		SELECT COUNT(*) > 0 FROM stat_download WHERE id = #{id} AND `date` = #{date}
	</select>
	
	<insert id="insert">
		INSERT INTO stat_download (id, sum, `date`) VALUES (#{id}, 1, #{date})
	</insert>
	
	<update id="increase">
		UPDATE stat_download SET sum = sum + 1 WHERE id = #{id} AND `date` = #{date}
	</update>
	
	<insert id="set">
		INSERT INTO stat_download (id, sum, `date`) VALUES
		(#{id}, #{sum}, #{date})
	</insert>

</mapper>